langchain_levers/__init__.py
langchain_levers/utils/__init__.py
langchain_levers/utils/constant.py
langchain_levers/utils/sparse.py
langchain_levers/vectorstores/__init__.py
langchain_levers/vectorstores/levers.py
langchain_levers-0.0.7.dist-info/LICENSE
langchain_levers-0.0.7.dist-info/METADATA
langchain_levers-0.0.7.dist-info/WHEEL
langchain_levers-0.0.7.dist-info/RECORD
