Metadata-Version: 2.3
Name: langchain-levers
Version: 0.0.7
Summary: LangChain levers.
License: MIT
Requires-Python: >=3.9,<3.12.4
Classifier: License :: OSI Approved :: MIT License
Classifier: Programming Language :: Python :: 3
Classifier: Programming Language :: Python :: 3.9
Classifier: Programming Language :: Python :: 3.10
Classifier: Programming Language :: Python :: 3.11
Classifier: Programming Language :: Python :: 3.12
Requires-Dist: langchain-core (>=0.2.38,<0.4)
Requires-Dist: pylevers
Project-URL: Repository, https://github.com/langchain-ai/langchain
